cortex_app/__init__.py
cortex_app-0.0.1.dist-info/METADATA
cortex_app-0.0.1.dist-info/WHEEL
cortex_app-0.0.1.dist-info/entry_points.txt
cortex_app-0.0.1.dist-info/licenses/LICENSE
cortex_app-0.0.1.dist-info/RECORD
