Metadata-Version: 2.4
Name: cortex-app
Version: 0.0.1
Summary: Cortex App - AI Agent Platform CLI (Coming Soon)
Project-URL: Homepage, https://cortex-app.ai
Project-URL: Documentation, https://docs.cortex-app.ai
Project-URL: Repository, https://github.com/cortex-app/cortex-cli
Project-URL: Issues, https://github.com/cortex-app/cortex-cli/issues
Project-URL: Changelog, https://github.com/cortex-app/cortex-cli/blob/main/CHANGELOG.md
Author-email: Cortex App <dev@cortex-app.ai>
License: MIT
License-File: LICENSE
Keywords: agents,ai,cli,cortex,mcp,platform
Classifier: Development Status :: 1 - Planning
Classifier: Intended Audience :: Developers
Classifier: License :: OSI Approved :: MIT License
Classifier: Programming Language :: Python :: 3
Classifier: Programming Language :: Python :: 3.8
Classifier: Programming Language :: Python :: 3.9
Classifier: Programming Language :: Python :: 3.10
Classifier: Programming Language :: Python :: 3.11
Classifier: Programming Language :: Python :: 3.12
Classifier: Topic :: Software Development :: Libraries :: Python Modules
Classifier: Topic :: Utilities
Requires-Python: >=3.8
